testgui/__init__.py
testgui/gui.py
testgui/unittestgui.py
testgui/assets/index.html
testgui/assets/lodash.min.js
testgui/assets/material-icons.css
testgui/assets/material-icons.woff2
testgui/assets/quasar.min.css
testgui/assets/quasar.umd.min.js
testgui/assets/script.js
testgui/assets/styles.css
testgui/assets/vue.min.js
testgui/management/__init__.py
testgui/management/commands/__init__.py
testgui/management/commands/testgui.py
testgui-0.3.dist-info/AUTHORS
testgui-0.3.dist-info/LICENSE
testgui-0.3.dist-info/METADATA
testgui-0.3.dist-info/WHEEL
testgui-0.3.dist-info/top_level.txt
testgui-0.3.dist-info/RECORD
