Metadata-Version: 2.1
Name: testgui
Version: 0.3
Summary: Drop-in replacement GUI for Django testing.
Home-page: https://github.com/BarnabasSzabolcs/testgui
Author: Barney Szabolcs
Author-email: szabolcs.barnabas@gmail.com
License: UNKNOWN
Keywords: test,django,management command,test GUI,GUI
Platform: UNKNOWN
Classifier: Framework :: Django
Classifier: Intended Audience :: Developers
Classifier: Operating System :: OS Independent
Classifier: Programming Language :: Python
Classifier: Programming Language :: Python :: 3
Classifier: License :: OSI Approved :: MIT License
Requires-Python: >=3.5
Requires-Dist: pywebview
Requires-Dist: ansi2html
